edc_stata/__init__.py
edc_stata/apps.py
edc_stata/models.py
edc_stata/urls.py
edc_stata/management/__init__.py
edc_stata/management/commands/__init__.py
edc_stata/management/commands/export_to_stata.py
edc_stata/tests/__init__.py
edc_stata/tests/etc/django_crypto_fields
edc_stata/tests/etc/user-aes-local.key
edc_stata/tests/etc/user-aes-restricted.key
edc_stata/tests/etc/user-rsa-local-private.pem
edc_stata/tests/etc/user-rsa-local-public.pem
edc_stata/tests/etc/user-rsa-restricted-private.pem
edc_stata/tests/etc/user-rsa-restricted-public.pem
edc_stata/tests/etc/user-salt-local.key
edc_stata/tests/etc/user-salt-restricted.key
edc_stata/tests/tests/__init__.py
edc_stata-0.1.0.dist-info/AUTHORS
edc_stata-0.1.0.dist-info/LICENSE
edc_stata-0.1.0.dist-info/METADATA
edc_stata-0.1.0.dist-info/WHEEL
edc_stata-0.1.0.dist-info/top_level.txt
edc_stata-0.1.0.dist-info/RECORD
